LICENSE
MANIFEST.in
README.rst
setup.py
thriftify/__init__.py
thriftify/command_line.py
thriftify/thriftExcelTools.py
thriftify.egg-info/PKG-INFO
thriftify.egg-info/SOURCES.txt
thriftify.egg-info/dependency_links.txt
thriftify.egg-info/entry_points.txt
thriftify.egg-info/not-zip-safe
thriftify.egg-info/requires.txt
thriftify.egg-info/top_level.txt