Metadata-Version: 2.1
Name: thriftify
Version: 0.1.5
Summary: Converts xlsx files into thrift binary or json blobs
Home-page: http://github.com/ohthepain/thriftify
Author: Paul Wilkinson
Author-email: paul@thisco.co
License: MIT
Keywords: thrift config
Classifier: Development Status :: 3 - Alpha
Classifier: License :: OSI Approved :: MIT License
Classifier: Programming Language :: Python :: 3.8
License-File: LICENSE
Requires-Dist: openpyxl
Requires-Dist: datetime
Requires-Dist: thrift
Requires-Dist: argparse
Requires-Dist: datetime
